MANIFEST.in
README.rst
setup.cfg
setup.py
./gwgen/__init__.py
./gwgen/evaluation.py
./gwgen/main.py
./gwgen/parameterization.py
./gwgen/parse_eecra.py
./gwgen/parseghcnrow.py
./gwgen/preproc.py
./gwgen/sensitivity_analysis.py
./gwgen/utils.py
./gwgen/version.py
gwgen/mo_parseeecra.f90
gwgen/mo_parseghcnrow.f90
gwgen.egg-info/PKG-INFO
gwgen.egg-info/SOURCES.txt
gwgen.egg-info/dependency_links.txt
gwgen.egg-info/entry_points.txt
gwgen.egg-info/not-zip-safe
gwgen.egg-info/requires.txt
gwgen.egg-info/top_level.txt
gwgen/data/eecra_ghcn_map.csv
gwgen/src/.git
gwgen/src/.gitignore
gwgen/src/LICENSE
gwgen/src/Makefile
gwgen/src/README.rst
gwgen/src/csv_file.f90
gwgen/src/csv_file_1d.f90
gwgen/src/csv_file_2d.f90
gwgen/src/geohashmod.f90
gwgen/src/main.f90
gwgen/src/parametersmod.f90
gwgen/src/randomdistmod.f90
gwgen/src/weathergen.nml
gwgen/src/weathergenmod.f90