Metadata-Version: 1.1
Name: gwgen
Version: 1.0.3
Summary: A global weather generator for daily data
Home-page: https://github.com/ARVE-Research/gwgen
Author: Philipp Sommer
Author-email: philipp.sommer@unil.ch
License: GPLv2
Keywords: wgen weathergen ghcn eecra richardson geng
Platform: UNKNOWN
Classifier: Development Status :: 5 - Production/Stable
Classifier: Intended Audience :: Developers
Classifier: Intended Audience :: Education
Classifier: Intended Audience :: Science/Research
Classifier: Topic :: Scientific/Engineering :: Physics
Classifier: Topic :: Scientific/Engineering
Classifier: License :: OSI Approved :: GNU General Public License v2 (GPLv2)
Classifier: Programming Language :: Python :: 2
Classifier: Programming Language :: Python :: 2.7
Classifier: Programming Language :: Python :: 3
Classifier: Programming Language :: Python :: 3.2
Classifier: Programming Language :: Python :: 3.3
Classifier: Programming Language :: Python :: 3.4
Classifier: Programming Language :: Python :: 3.5
Classifier: Operating System :: Unix
Classifier: Operating System :: MacOS
